eleanor-0.0.1.dist-info/METADATA
eleanor-0.0.1.dist-info/RECORD
eleanor-0.0.1.dist-info/WHEEL
eleanor-0.0.1.dist-info/top_level.txt
ellie/__init__.py
ellie/click_for_lc_website.py
ellie/data_product.py
ellie/download.py
ellie/ellie.py
ellie/ffi.py
ellie/find_star.py
ellie/logo.py
ellie/mast.py
ellie/movie.py
ellie/planetExample.py
ellie/pm.py
ellie/postcard.py
ellie/source.py
ellie/testing.py
ellie/track_pm_centroid.py
ellie/visualize.py
