Metadata-Version: 2.1
Name: eleanor
Version: 0.0.1
Summary: Source Extraction for TESS Full Frame Images
Home-page: http://github.com/afeinstein20/ELLIE
Author: Adina D. Feinstein
Author-email: adina.d.feinstein@gmail.com
License: MIT
Platform: UNKNOWN
Classifier: Development Status :: 3 - Alpha
Classifier: Intended Audience :: Science/Research
Classifier: License :: OSI Approved :: MIT License
Classifier: Operating System :: OS Independent
Classifier: Programming Language :: Python :: 3.0
Requires-Dist: mplcursors
Requires-Dist: photutils
Requires-Dist: tqdm
Requires-Dist: lightkurve
Requires-Dist: astropy
Requires-Dist: astroquery
Requires-Dist: bokeh
Requires-Dist: muchbettermoments
